mlx_voxtral/__init__.py
mlx_voxtral/audio_processing.py
mlx_voxtral/configuration_voxtral.py
mlx_voxtral/modeling_voxtral.py
mlx_voxtral/processing_voxtral.py
mlx_voxtral/quantization.py
mlx_voxtral/models/__init__.py
mlx_voxtral/models/llama.py
mlx_voxtral/scripts/__init__.py
mlx_voxtral/scripts/generate.py
mlx_voxtral/scripts/quantize_voxtral.py
mlx_voxtral/utils/__init__.py
mlx_voxtral/utils/model_loading.py
mlx_voxtral-0.0.4.dist-info/licenses/LICENSE
mlx_voxtral-0.0.4.dist-info/METADATA
mlx_voxtral-0.0.4.dist-info/WHEEL
mlx_voxtral-0.0.4.dist-info/entry_points.txt
mlx_voxtral-0.0.4.dist-info/top_level.txt
mlx_voxtral-0.0.4.dist-info/RECORD
