Metadata-Version: 2.4
Name: mlx-voxtral
Version: 0.0.4
Summary: Voxtral audio processing and model implementation for Apple Silicon using MLX
Author: Anchen Li
License: Personal Use Only - See LICENSE file
Project-URL: Repository, https://github.com/mzbac/mlx.voxtral
Project-URL: Issues, https://github.com/mzbac/mlx.voxtral/issues
Keywords: mlx,voxtral,whisper,audio,speech,apple-silicon
Requires-Python: >=3.11
License-File: LICENSE
Requires-Dist: mistral-common>=1.8.2
Requires-Dist: mlx>=0.26.5
Requires-Dist: mlx-lm>=0.26.0
Requires-Dist: numpy<2.3.0,>=1.22.4
Requires-Dist: protobuf<6.0,>=3.19.0
Requires-Dist: soundfile>=0.12.0
Requires-Dist: soxr>=0.5.0
Requires-Dist: transformers>=4.55.2
Dynamic: license-file
